lab1_ring_flasher/ring_flasher.v
module ring_flasher(
    input clk,
    input rst,     // active LOW
    input rep,
    output reg [15:0] leds
);

reg [3:0] counter;
reg [1:0] state;
reg temp;

localparam IDLE     = 2'd0;
localparam FORWARD  = 2'd1;
localparam BACKWARD = 2'd2;

always @(posedge clk or negedge rst) begin 
    if (!rst) begin
        leds <= 16'b0;
        counter <= 0;
        state <= FORWARD;
    end
    else begin

        case (state)
        // 🔹 Forward 8 steps
        FORWARD: begin
            temp = leds[15] ^ 1'b1;
            leds <= {leds[14:0], temp};
            counter <= counter + 1;

            if (counter == 4'd7) begin
                counter <= 0;
                state <= BACKWARD;
            end
        end

        // 🔹 Backward 4 steps
        BACKWARD: begin
            temp = leds[0] ^ 1'b1;
            leds <= {temp, leds[15:1]};
            counter <= counter + 1;

            if(leds == 16'b0)
                state <= IDLE;

            else if(counter == 4'd3) begin
                counter <= 0;
                state <= FORWARD;
            end
        end

        // 🔹 Wait for rep
        IDLE: begin
            leds <= 16'b0;

            if (rep) begin
                counter <= 0;
                state <= FORWARD;
            end
        end

        endcase
    end
end

endmodule

lab1_ring_flasher/testbench_ring_flasher.v
module ring_flasher_tb;

    reg clk;
    reg rst;
    reg rep;
    wire [15:0] leds;

    // Instantiate DUT
    ring_flasher uut (
        .clk(clk),
        .rst(rst),
        .rep(rep),
        .leds(leds)
    );

    // Expose internal signals for monitoring
    wire [3:0] counter = uut.counter;
    wire [1:0] state   = uut.state;

    // Clock generation (10ns period)
    initial clk = 0;
    always #5 clk = ~clk;

    // Stimulus
    initial begin
        $dumpfile("ring_flasher.vcd");
        $dumpvars(0, ring_flasher_tb);

        // Initialize
        rst = 1;
        rep = 0;

        // Assert active-low reset
        @(negedge clk); rst = 0;
        #20;
        rst = 1;

        // Wait for FORWARD -> BACKWARD -> IDLE cycle
        #500;

        // Trigger rep in IDLE
        @(negedge clk); rep = 1;
        #10;
        rep = 0;

        // Wait for another full cycle
        #500;

        // Trigger rep again
        @(negedge clk); rep = 1;
        #10;
        rep = 0;

        #300;
        $stop;
    end

    // Monitor
    initial begin
        $monitor("Time=%0t | rst=%b rep=%b state=%b counter=%0d leds=%b",
                  $time, rst, rep, state, counter, leds);
    end

endmodule

lab1_ring_flasher/ring_flasher.vcd
$date
	Wed Apr 15 12:28:13 2026
$end
$version
	Icarus Verilog
$end
$timescale
	1s
$end
$scope module ring_flasher_tb $end
$var wire 4 ! counter [3:0] $end
$var wire 2 " state [1:0] $end
$var wire 16 # leds [15:0] $end
$var reg 1 $ clk $end
$var reg 1 % rep $end
$var reg 1 & rst $end
$scope module uut $end
$var wire 1 $ clk $end
$var wire 1 % rep $end
$var wire 1 & rst $end
$var parameter 2 ' BACKWARD $end
$var parameter 2 ( FORWARD $end
$var parameter 2 ) IDLE $end
$var reg 4 * counter [3:0] $end
$var reg 16 + leds [15:0] $end
$var reg 2 , state [1:0] $end
$var reg 1 - temp $end
$upscope $end
$upscope $end
$enddefinitions $end
$comment Show the parameter values. $end
$dumpall
b0 )
b1 (
b10 '
$end
#0
$dumpvars
x-
bx ,
bx +
bx *
1&
0%
0$
bx #
bx "
bx !
$end
#5
1$
#10
b1 "
b1 ,
b0 !
b0 *
b0 #
b0 +
0&
0$
#15
1$
#20
0$
#25
1$
#30
0$
1&
#35
b1 !
b1 *
b1 #
b1 +
1-
1$
#40
0$
#45
b10 !
b10 *
b11 #
b11 +
1$
#50
0$
#55
b11 !
b11 *
b111 #
b111 +
1$
#60
0$
#65
b100 !
b100 *
b1111 #
b1111 +
1$
#70
0$
#75
b101 !
b101 *
b11111 #
b11111 +
1$
#80
0$
#85
b110 !
b110 *
b111111 #
b111111 +
1$
#90
0$
#95
b111 !
b111 *
b1111111 #
b1111111 +
1$
#100
0$
#105
b10 "
b10 ,
b0 !
b0 *
b11111111 #
b11111111 +
1$
#110
0$
#115
b1 !
b1 *
b1111111 #
b1111111 +
0-
1$
#120
0$
#125
b10 !
b10 *
b111111 #
b111111 +
1$
#130
0$
#135
b11 !
b11 *
b11111 #
b11111 +
1$
#140
0$
#145
b1 "
b1 ,
b0 !
b0 *
b1111 #
b1111 +
1$
#150
0$
#155
b1 !
b1 *
b11111 #
b11111 +
1-
1$
#160
0$
#165
b10 !
b10 *
b111111 #
b111111 +
1$
#170
0$
#175
b11 !
b11 *
b1111111 #
b1111111 +
1$
#180
0$
#185
b100 !
b100 *
b11111111 #
b11111111 +
1$
#190
0$
#195
b101 !
b101 *
b111111111 #
b111111111 +
1$
#200
0$
#205
b110 !
b110 *
b1111111111 #
b1111111111 +
1$
#210
0$
#215
b111 !
b111 *
b11111111111 #
b11111111111 +
1$
#220
0$
#225
b10 "
b10 ,
b0 !
b0 *
b111111111111 #
b111111111111 +
1$
#230
0$
#235
b1 !
b1 *
b11111111111 #
b11111111111 +
0-
1$
#240
0$
#245
b10 !
b10 *
b1111111111 #
b1111111111 +
1$
#250
0$
#255
b11 !
b11 *
b111111111 #
b111111111 +
1$
#260
0$
#265
b1 "
b1 ,
b0 !
b0 *
b11111111 #
b11111111 +
1$
#270
0$
#275
b1 !
b1 *
b111111111 #
b111111111 +
1-
1$
#280
0$
#285
b10 !
b10 *
b1111111111 #
b1111111111 +
1$
#290
0$
#295
b11 !
b11 *
b11111111111 #
b11111111111 +
1$
#300
0$
#305
b100 !
b100 *
b111111111111 #
b111111111111 +
1$
#310
0$
#315
b101 !
b101 *
b1111111111111 #
b1111111111111 +
1$
#320
0$
#325
b110 !
b110 *
b11111111111111 #
b11111111111111 +
1$
#330
0$
#335
b111 !
b111 *
b111111111111111 #
b111111111111111 +
1$
#340
0$
#345
b10 "
b10 ,
b0 !
b0 *
b1111111111111111 #
b1111111111111111 +
1$
#350
0$
#355
b1 !
b1 *
b111111111111111 #
b111111111111111 +
0-
1$
#360
0$
#365
b10 !
b10 *
b11111111111111 #
b11111111111111 +
1$
#370
0$
#375
b11 !
b11 *
b1111111111111 #
b1111111111111 +
1$
#380
0$
#385
b1 "
b1 ,
b0 !
b0 *
b111111111111 #
b111111111111 +
1$
#390
0$
#395
b1 !
b1 *
b1111111111111 #
b1111111111111 +
1-
1$
#400
0$
#405
b10 !
b10 *
b11111111111111 #
b11111111111111 +
1$
#410
0$
#415
b11 !
b11 *
b111111111111111 #
b111111111111111 +
1$
#420
0$
#425
b100 !
b100 *
b1111111111111111 #
b1111111111111111 +
1$
#430
0$
#435
b101 !
b101 *
b1111111111111110 #
b1111111111111110 +
0-
1$
#440
0$
#445
b110 !
b110 *
b1111111111111100 #
b1111111111111100 +
1$
#450
0$
#455
b111 !
b111 *
b1111111111111000 #
b1111111111111000 +
1$
#460
0$
#465
b10 "
b10 ,
b0 !
b0 *
b1111111111110000 #
b1111111111110000 +
1$
#470
0$
#475
b1 !
b1 *
b1111111111111000 #
b1111111111111000 +
1-
1$
#480
0$
#485
b10 !
b10 *
b1111111111111100 #
b1111111111111100 +
1$
#490
0$
#495
b11 !
b11 *
b1111111111111110 #
b1111111111111110 +
1$
#500
0$
#505
b1 "
b1 ,
b0 !
b0 *
b1111111111111111 #
b1111111111111111 +
1$
#510
0$
#515
b1 !
b1 *
b1111111111111110 #
b1111111111111110 +
0-
1$
#520
0$
#525
b10 !
b10 *
b1111111111111100 #
b1111111111111100 +
1$
#530
1%
0$
#535
b11 !
b11 *
b1111111111111000 #
b1111111111111000 +
1$
#540
0$
0%
#545
b100 !
b100 *
b1111111111110000 #
b1111111111110000 +
1$
#550
0$
#555
b101 !
b101 *
b1111111111100000 #
b1111111111100000 +
1$
#560
0$
#565
b110 !
b110 *
b1111111111000000 #
b1111111111000000 +
1$
#570
0$
#575
b111 !
b111 *
b1111111110000000 #
b1111111110000000 +
1$
#580
0$
#585
b10 "
b10 ,
b0 !
b0 *
b1111111100000000 #
b1111111100000000 +
1$
#590
0$
#595
b1 !
b1 *
b1111111110000000 #
b1111111110000000 +
1-
1$
#600
0$
#605
b10 !
b10 *
b1111111111000000 #
b1111111111000000 +
1$
#610
0$
#615
b11 !
b11 *
b1111111111100000 #
b1111111111100000 +
1$
#620
0$
#625
b1 "
b1 ,
b0 !
b0 *
b1111111111110000 #
b1111111111110000 +
1$
#630
0$
#635
b1 !
b1 *
b1111111111100000 #
b1111111111100000 +
0-
1$
#640
0$
#645
b10 !
b10 *
b1111111111000000 #
b1111111111000000 +
1$
#650
0$
#655
b11 !
b11 *
b1111111110000000 #
b1111111110000000 +
1$
#660
0$
#665
b100 !
b100 *
b1111111100000000 #
b1111111100000000 +
1$
#670
0$
#675
b101 !
b101 *
b1111111000000000 #
b1111111000000000 +
1$
#680
0$
#685
b110 !
b110 *
b1111110000000000 #
b1111110000000000 +
1$
#690
0$
#695
b111 !
b111 *
b1111100000000000 #
b1111100000000000 +
1$
#700
0$
#705
b10 "
b10 ,
b0 !
b0 *
b1111000000000000 #
b1111000000000000 +
1$
#710
0$
#715
b1 !
b1 *
b1111100000000000 #
b1111100000000000 +
1-
1$
#720
0$
#725
b10 !
b10 *
b1111110000000000 #
b1111110000000000 +
1$
#730
0$
#735
b11 !
b11 *
b1111111000000000 #
b1111111000000000 +
1$
#740
0$
#745
b1 "
b1 ,
b0 !
b0 *
b1111111100000000 #
b1111111100000000 +
1$
#750
0$
#755
b1 !
b1 *
b1111111000000000 #
b1111111000000000 +
0-
1$
#760
0$
#765
b10 !
b10 *
b1111110000000000 #
b1111110000000000 +
1$
#770
0$
#775
b11 !
b11 *
b1111100000000000 #
b1111100000000000 +
1$
#780
0$
#785
b100 !
b100 *
b1111000000000000 #
b1111000000000000 +
1$
#790
0$
#795
b101 !
b101 *
b1110000000000000 #
b1110000000000000 +
1$
#800
0$
#805
b110 !
b110 *
b1100000000000000 #
b1100000000000000 +
1$
#810
0$
#815
b111 !
b111 *
b1000000000000000 #
b1000000000000000 +
1$
#820
0$
#825
b10 "
b10 ,
b0 !
b0 *
b0 #
b0 +
1$
#830
0$
#835
b0 "
b0 ,
b1 !
b1 *
b1000000000000000 #
b1000000000000000 +
1-
1$
#840
0$
#845
b0 #
b0 +
1$
#850
0$
#855
1$
#860
0$
#865
1$
#870
0$
#875
1$
#880
0$
#885
1$
#890
0$
#895
1$
#900
0$
#905
1$
#910
0$
#915
1$
#920
0$
#925
1$
#930
0$
#935
1$
#940
0$
#945
1$
#950
0$
#955
1$
#960
0$
#965
1$
#970
0$
#975
1$
#980
0$
#985
1$
#990
0$
#995
1$
#1000
0$
#1005
1$
#1010
0$
#1015
1$
#1020
0$
#1025
1$
#1030
0$
#1035
1$
#1040
1%
0$
#1045
b1 "
b1 ,
b0 !
b0 *
1$
#1050
0$
0%
#1055
b1 !
b1 *
b1 #
b1 +
1$
#1060
0$
#1065
b10 !
b10 *
b11 #
b11 +
1$
#1070
0$
#1075
b11 !
b11 *
b111 #
b111 +
1$
#1080
0$
#1085
b100 !
b100 *
b1111 #
b1111 +
1$
#1090
0$
#1095
b101 !
b101 *
b11111 #
b11111 +
1$
#1100
0$
#1105
b110 !
b110 *
b111111 #
b111111 +
1$
#1110
0$
#1115
b111 !
b111 *
b1111111 #
b1111111 +
1$
#1120
0$
#1125
b10 "
b10 ,
b0 !
b0 *
b11111111 #
b11111111 +
1$
#1130
0$
#1135
b1 !
b1 *
b1111111 #
b1111111 +
0-
1$
#1140
0$
#1145
b10 !
b10 *
b111111 #
b111111 +
1$
#1150
0$
#1155
b11 !
b11 *
b11111 #
b11111 +
1$
#1160
0$
#1165
b1 "
b1 ,
b0 !
b0 *
b1111 #
b1111 +
1$
#1170
0$
#1175
b1 !
b1 *
b11111 #
b11111 +
1-
1$
#1180
0$
#1185
b10 !
b10 *
b111111 #
b111111 +
1$
#1190
0$
#1195
b11 !
b11 *
b1111111 #
b1111111 +
1$
#1200
0$
#1205
b100 !
b100 *
b11111111 #
b11111111 +
1$
#1210
0$
#1215
b101 !
b101 *
b111111111 #
b111111111 +
1$
#1220
0$
#1225
b110 !
b110 *
b1111111111 #
b1111111111 +
1$
#1230
0$
#1235
b111 !
b111 *
b11111111111 #
b11111111111 +
1$
#1240
0$
#1245
b10 "
b10 ,
b0 !
b0 *
b111111111111 #
b111111111111 +
1$
#1250
0$
#1255
b1 !
b1 *
b11111111111 #
b11111111111 +
0-
1$
#1260
0$
#1265
b10 !
b10 *
b1111111111 #
b1111111111 +
1$
#1270
0$
#1275
b11 !
b11 *
b111111111 #
b111111111 +
1$
#1280
0$
#1285
b1 "
b1 ,
b0 !
b0 *
b11111111 #
b11111111 +
1$
#1290
0$
#1295
b1 !
b1 *
b111111111 #
b111111111 +
1-
1$
#1300
0$
#1305
b10 !
b10 *
b1111111111 #
b1111111111 +
1$
#1310
0$
#1315
b11 !
b11 *
b11111111111 #
b11111111111 +
1$
#1320
0$
#1325
b100 !
b100 *
b111111111111 #
b111111111111 +
1$
#1330
0$
#1335
b101 !
b101 *
b1111111111111 #
b1111111111111 +
1$
#1340
0$
#1345
b110 !
b110 *
b11111111111111 #
b11111111111111 +
1$
